tony_ml/__init__.py
tony_ml/automl.py
tony_ml/main.py
tony_ml-1.0.5.dist-info/LICENSE.txt
tony_ml-1.0.5.dist-info/METADATA
tony_ml-1.0.5.dist-info/WHEEL
tony_ml-1.0.5.dist-info/top_level.txt
tony_ml-1.0.5.dist-info/RECORD
